clj/__init__.py
clj/fns.py
clj/py.typed
clj/seqs.py
clj-0.5.0.dist-info/LICENSE
clj-0.5.0.dist-info/METADATA
clj-0.5.0.dist-info/WHEEL
clj-0.5.0.dist-info/RECORD
