Metadata-Version: 2.3
Name: clj
Version: 0.5.0
Summary: Utilities for lazy iterables
License: MIT
Keywords: clj,clojure,lazy,iterables,generators
Author: Baptiste Fontaine
Author-email: b@ptistefontaine.fr
Requires-Python: >=3.9,<4.0
Classifier: Development Status :: 5 - Production/Stable
Classifier: License :: OSI Approved :: MIT License
Classifier: Programming Language :: Python :: 3
Classifier: Programming Language :: Python :: 3.9
Classifier: Programming Language :: Python :: 3.10
Classifier: Programming Language :: Python :: 3.11
Classifier: Programming Language :: Python :: 3.12
Classifier: Programming Language :: Python :: 3.13
Project-URL: Homepage, https://github.com/bfontaine/clj
Project-URL: Repository, https://github.com/bfontaine/clj
